make_preset/__init__.py
make_preset/preset.py
make_preset-1.0.3.dist-info/METADATA
make_preset-1.0.3.dist-info/WHEEL
make_preset-1.0.3.dist-info/top_level.txt
make_preset-1.0.3.dist-info/RECORD
