Metadata-Version: 2.1
Name: make-preset
Version: 1.0.3
Summary: SETTING PRESET
Home-page: UNKNOWN
Author: Hyeonjinkk
Author-email: guswls0975@naver.com
License: MIT
Platform: UNKNOWN
Requires-Python: >=3
